lib/openxes-cli.jar
openxes_cli/__init__.py
openxes_cli/lib.py
openxes_cli_py-0.1.15.dist-info/METADATA
openxes_cli_py-0.1.15.dist-info/WHEEL
openxes_cli_py-0.1.15.dist-info/RECORD
