Metadata-Version: 2.1
Name: openxes-cli-py
Version: 0.1.15
Summary: 
Author: Ihar Suvorau
Author-email: ihar.suvorau@gmail.com
Requires-Python: >=3.9,<4.0
Classifier: Programming Language :: Python :: 3
Classifier: Programming Language :: Python :: 3.9
Classifier: Programming Language :: Python :: 3.10
Classifier: Programming Language :: Python :: 3.11
